faster_whisper_cli/__init__.py
faster_whisper_cli/cli.py
faster_whisper_cli-1.0.1.dist-info/entry_points.txt
faster_whisper_cli-1.0.1.dist-info/METADATA
faster_whisper_cli-1.0.1.dist-info/WHEEL
faster_whisper_cli-1.0.1.dist-info/RECORD
